AUTHORS.rst
CONTRIBUTING.rst
HISTORY.rst
LICENSE
MANIFEST.in
README.rst
setup.cfg
setup.py
docs/Makefile
docs/authors.rst
docs/conf.py
docs/contributing.rst
docs/history.rst
docs/index.rst
docs/installation.rst
docs/make.bat
docs/modules.rst
docs/pyramid_sms.rst
docs/readme.rst
docs/usage.rst
pyramid_sms/__init__.py
pyramid_sms/dummy.py
pyramid_sms/events.py
pyramid_sms/interfaces.py
pyramid_sms/outgoing.py
pyramid_sms/ovh.py
pyramid_sms/twilio.py
pyramid_sms/utils.py
pyramid_sms/validators.py
pyramid_sms.egg-info/PKG-INFO
pyramid_sms.egg-info/SOURCES.txt
pyramid_sms.egg-info/dependency_links.txt
pyramid_sms.egg-info/not-zip-safe
pyramid_sms.egg-info/requires.txt
pyramid_sms.egg-info/top_level.txt
tests/__init__.py
tests/test_normalize.py
tests/test_pyramid_sms.py
tests/test_valid.py