Metadata-Version: 2.1
Name: pyramid-sms
Version: 0.1.4
Summary: SMS service framework for Pyramid
Home-page: https://github.com/miohtama/pyramid_sms
Author: Mikko Ohtamaa
Author-email: mikko@opensourcehacker.com
License: ISCL
Keywords: pyramid sms
Platform: UNKNOWN
Classifier: Development Status :: 2 - Pre-Alpha
Classifier: Intended Audience :: Developers
Classifier: License :: OSI Approved :: ISC License (ISCL)
Classifier: Natural Language :: English
Classifier: Programming Language :: Python :: 3
Classifier: Programming Language :: Python :: 3.4
Classifier: Programming Language :: Python :: 3.5
Classifier: Framework :: Pyramid
Provides-Extra: twilio
